s3dol/__init__.py
s3dol/base.py
s3dol/store.py
s3dol/utility.py
s3dol/tests/__init__.py
s3dol/tests/test_base.py
s3dol/tests/test_store.py
s3dol/tests/util.py
s3dol-0.1.8.dist-info/LICENSE
s3dol-0.1.8.dist-info/METADATA
s3dol-0.1.8.dist-info/WHEEL
s3dol-0.1.8.dist-info/top_level.txt
s3dol-0.1.8.dist-info/RECORD
