Metadata-Version: 2.1
Name: s3dol
Version: 0.1.8
Summary: s3 (through boto3) with a simple (dict-like or list-like) interface
Home-page: https://github.com/i2mint/s3dol
License: apache-2.0
Platform: any
License-File: LICENSE
Requires-Dist: dol
Requires-Dist: botocore
Requires-Dist: boto3
